rclone.py
python_rclone-0.0.2.dist-info/METADATA
python_rclone-0.0.2.dist-info/RECORD
python_rclone-0.0.2.dist-info/WHEEL
python_rclone-0.0.2.dist-info/top_level.txt
