Metadata-Version: 2.1
Name: python-rclone
Version: 0.0.2
Summary: Rclone wrapper for python
Home-page: https://github.com/ddragosd/python-rclone
Author: Dragos Dascalita Haut
Author-email: ddragosd@gmail.com
License: UNKNOWN
Platform: UNKNOWN
Classifier: Programming Language :: Python :: 3
Classifier: License :: OSI Approved :: Apache Software License
